fictional_names/.gitignore
fictional_names/__init__.py
fictional_names/arab.py
fictional_names/aztec.py
fictional_names/chinese.py
fictional_names/dragonborn.py
fictional_names/drow.py
fictional_names/dwarven.py
fictional_names/elven.py
fictional_names/english.py
fictional_names/erikson.py
fictional_names/germanic.py
fictional_names/giant.py
fictional_names/gnomish.py
fictional_names/greek.py
fictional_names/halfling.py
fictional_names/human.py
fictional_names/japanese.py
fictional_names/jordan.py
fictional_names/martin.py
fictional_names/mongolian.py
fictional_names/name_generator.py
fictional_names/norsemen.py
fictional_names/orc.py
fictional_names/roman.py
fictional_names/rowling.py
fictional_names/sapkowski.py
fictional_names/slavic.py
fictional_names/steampunk.py
fictional_names/supportive_functions.py
fictional_names/tolkien.py
fictional_names/turkish.py
fictional_names/viking.py
fictional_names-1.0.0.dist-info/METADATA
fictional_names-1.0.0.dist-info/WHEEL
fictional_names-1.0.0.dist-info/licenses/LICENSE
fictional_names-1.0.0.dist-info/RECORD
