Metadata-Version: 2.4
Name: fictional_names
Version: 1.0.0
Summary: A package for generating fictional names.
Project-URL: Homepage, https://github.com/a-tsagkalidis/fictional_names_package
Project-URL: Bug Tracker, https://github.com/a-tsagkalidis/fictional_names_package/issues
Author-email: a-tsagkalidis <arg.tsag@gmail.com>
License-File: LICENSE
Classifier: License :: OSI Approved :: MIT License
Classifier: Operating System :: OS Independent
Classifier: Programming Language :: Python :: 3
Requires-Python: >=3.7
